realtimeregister/__init__.py
realtimeregister/client.py
realtimeregister/exceptions.py
realtimeregister/api/__init__.py
realtimeregister/api/abuse.py
realtimeregister/api/billing.py
realtimeregister/api/brands.py
realtimeregister/api/certificates.py
realtimeregister/api/contacts.py
realtimeregister/api/customers.py
realtimeregister/api/dns.py
realtimeregister/api/domains.py
realtimeregister/api/notifications.py
realtimeregister/api/processes.py
realtimeregister/api/providers.py
realtimeregister/api/reseller.py
realtimeregister/api/statistics.py
realtimeregister/api/templates.py
realtimeregister/api/tlds.py
realtimeregister/api/transfers.py
realtimeregister/enums/__init__.py
realtimeregister/enums/abuse_status.py
realtimeregister/enums/billing_type.py
realtimeregister/enums/certificate_type.py
realtimeregister/enums/certificate_validation_method.py
realtimeregister/enums/domain_status.py
realtimeregister/enums/invoice_status.py
realtimeregister/enums/launch_phase.py
realtimeregister/enums/notification_type.py
realtimeregister/enums/process_status.py
realtimeregister/enums/provider_status.py
realtimeregister/enums/provider_type.py
realtimeregister/enums/template_type.py
realtimeregister/enums/transaction_type.py
realtimeregister/enums/transfer_status.py
realtimeregister/enums/validation_status.py
realtimeregister/models/__init__.py
realtimeregister/models/abuse.py
realtimeregister/models/brand.py
realtimeregister/models/certificate.py
realtimeregister/models/contact.py
realtimeregister/models/customer.py
realtimeregister/models/dns_record.py
realtimeregister/models/domain.py
realtimeregister/models/invoice.py
realtimeregister/models/nameserver.py
realtimeregister/models/notification.py
realtimeregister/models/price.py
realtimeregister/models/process.py
realtimeregister/models/provider.py
realtimeregister/models/statistics.py
realtimeregister/models/template.py
realtimeregister/models/tld.py
realtimeregister/models/transaction.py
realtimeregister/models/transfer.py
realtimeregister-1.0.1.dist-info/METADATA
realtimeregister-1.0.1.dist-info/WHEEL
realtimeregister-1.0.1.dist-info/top_level.txt
realtimeregister-1.0.1.dist-info/RECORD
